{
  "image": {
    "room": [ 1, 8 , [ 0, 0, 0 ], [ 0, 8, 0 ] ]
  },
  "set": [
    ["+", "flag", "A", 1]
  ],
  "message": "北の扉に耳をつけてみた\n",
  "if": [
    ["=", "flag", "A", 0, {
      "message": "扉の向こうからは、ガシャガシャと金属が擦れる音が聞こえる。\n間違いなく鎧を来た人形の生き物の動きだ！\nこの迷宮に友好的な生き物などいるはずがない。\n気をつけなければ…"
    }],
    ["=", "flag", "A", 1, {
      "message": "扉の向こうからは、鎧を着た人間型の生き物の歩く音が聞こえる。\n足音は扉から徐々に遠ざかっている。\nおそらく敵だろうが、今なら隙を突いて有利にことを進められるかもしれない。"
    }],
    ["=", "flag", "A", 2, {
      "message": "扉の向こうからは、はるか遠くに鎧を着た人間型の生き物の歩く音が聞こえる。\nすぐには遭遇しないだろう遠い距離だ"
    }],
    ["=", "flag", "A", 3, {
      "message": "扉の向こうからは、鎧を着た人間型の生き物の歩く音が聞こえる。\n足音は扉に徐々に近づいている。\n遭遇すれば危険な状況になるだろう"
    }],
    [0, 0, 0, 0, {
      "set": [["=", "flag", "A", 1]],
      "message": "扉の向こうからは、ガシャガシャと金属が擦れる音が聞こえる。\n間違いなく鎧を来た人形の生き物の動きだ！\nこの迷宮に友好的な生き物などいるはずがない。\n気をつけなければ…"
    }]
  ],
  "prev": "1_6"
}
